{"cameraMode":{"drawMode":0,"name":"Shaded","section":"Shading Mode"},"sceneLighting":false,"audioPlay":false,"sceneViewState":{"showFog":true,"showMaterialUpdate":false,"showSkybox":false,"showFlares":true,"showImageEffects":true,"showParticleSystems":true,"showVisualEffectGraphs":true,"m_FxEnabled":true},"in2DMode":false,"pivot":{"x":355.0,"y":199.5,"z":0.0},"rotation":{"x":0.06861227750778198,"y":-0.027828017249703409,"z":-0.0019636040087789299,"w":-0.9973110556602478},"size":403.927978515625,"orthographic":false}